<?xml version="1.0" encoding="utf-8" ?>
<dwsync>
<file name="attributes.html" server="D:/xampp/htdocs/ECMS/" local="130681431586680936" remote="130681431580000000" Dst="1" />
<file name="custom.html" server="D:/xampp/htdocs/ECMS/" local="130681431586720936" remote="130681431580000000" Dst="1" />
<file name="elements.html" server="D:/xampp/htdocs/ECMS/" local="130681431586760936" remote="130681431580000000" Dst="1" />
<file name="event.html" server="D:/xampp/htdocs/ECMS/" local="130681431586820936" remote="130681431580000000" Dst="1" />
<file name="index.html" server="D:/xampp/htdocs/ECMS/" local="130681431586860936" remote="130681431580000000" Dst="1" />
<file name="remote-binding.html" server="D:/xampp/htdocs/ECMS/" local="130681431586910936" remote="130681431580000000" Dst="1" />
<file name="source.html" server="D:/xampp/htdocs/ECMS/" local="130681431586970936" remote="130681431580000000" Dst="1" />
<file name="style.html" server="D:/xampp/htdocs/ECMS/" local="130681431587020936" remote="130681431580000000" Dst="1" />
<file name="widgets.html" server="D:/xampp/htdocs/ECMS/" local="130681431587070936" remote="130681431580000000" Dst="1" />
<file name="attributes.html" server="Z:/ECMS/app/" local="130686538102447165" remote="130686538100000000" Dst="1" />
<file name="custom.html" server="Z:/ECMS/app/" local="130686538102447165" remote="130686538100000000" Dst="1" />
<file name="elements.html" server="Z:/ECMS/app/" local="130686538103247037" remote="130686538100000000" Dst="1" />
<file name="event.html" server="Z:/ECMS/app/" local="130686538103247037" remote="130686538100000000" Dst="1" />
<file name="index.html" server="Z:/ECMS/app/" local="130686538103347021" remote="130686538100000000" Dst="1" />
<file name="remote-binding.html" server="Z:/ECMS/app/" local="130686538103347021" remote="130686538100000000" Dst="1" />
<file name="source.html" server="Z:/ECMS/app/" local="130686538103447005" remote="130686538100000000" Dst="1" />
<file name="style.html" server="Z:/ECMS/app/" local="130686538103546989" remote="130686538100000000" Dst="1" />
<file name="widgets.html" server="Z:/ECMS/app/" local="130686538103546989" remote="130686538100000000" Dst="1" />
</dwsync>